synch2jira/__init__.py
synch2jira/config_handler.py
synch2jira/config_package.py
synch2jira/data_mining.py
synch2jira/datamining.py
synch2jira/historique.py
synch2jira/historique_issue.py
synch2jira/issue.py
synch2jira/issue_S1.py
synch2jira/issue_S2.py
synch2jira/issue_S3.py
synch2jira/issue_csv.py
synch2jira/issue_json.py
synch2jira/issue_wokflow.py
synch2jira/issue_wokflow_json.py
synch2jira/issue_workflow.py
synch2jira/issue_workflow_json.py
synch2jira/log.py
synch2jira/mix.py
synch2jira/status.py
synch2jira/synch.py
synch2jira/table_correpondance_key_id.py
synch2jira/workflow.py
synch2jira-0.0.221.dist-info/METADATA
synch2jira-0.0.221.dist-info/WHEEL
synch2jira-0.0.221.dist-info/top_level.txt
synch2jira-0.0.221.dist-info/RECORD
