Metadata-Version: 2.1
Name: synch2jira
Version: 0.0.221
Summary: Lib
Author: wefine
Author-email: wefine2529@ebuthor.com
License: MIT
Classifier: Programming Language :: Python :: 3
Classifier: License :: OSI Approved :: MIT License
Classifier: Operating System :: OS Independent
Requires-Dist: requests ==2.31.0
Requires-Dist: setuptools ==68.2.0
Requires-Dist: SQLAlchemy ==2.0.25
Requires-Dist: pandas
